setup.cfg
setup.py
retinex_for_mri/__init__.py
retinex_for_mri/conversions.py
retinex_for_mri/core.py
retinex_for_mri/filters.py
retinex_for_mri/utils.py
retinex_for_mri.egg-info/PKG-INFO
retinex_for_mri.egg-info/SOURCES.txt
retinex_for_mri.egg-info/dependency_links.txt
retinex_for_mri.egg-info/requires.txt
retinex_for_mri.egg-info/top_level.txt
retinex_for_mri.egg-info/zip-safe