Metadata-Version: 1.1
Name: retinex-for-mri
Version: 0.2.7
Summary: Retinex algorithm for MRI data.
Home-page: https://github.com/ofgulban/retinex_for_mri
Author: Omer Faruk Gulban
Author-email: faruk.gulban@maastrichtuniversity.nl
License: GNU Geneal Public License Version 3
Download-URL: https://github.com/ofgulban/retinex_for_mri/tarball/0.2.7
Keywords: mri
Platform: UNKNOWN
